lockss/debugpanel/__init__.py
lockss/debugpanel/__main__.py
lockss/debugpanel/cli.py
lockss_debugpanel-0.8.1.dist-info/LICENSE
lockss_debugpanel-0.8.1.dist-info/METADATA
lockss_debugpanel-0.8.1.dist-info/WHEEL
lockss_debugpanel-0.8.1.dist-info/entry_points.txt
lockss_debugpanel-0.8.1.dist-info/RECORD
